odoo/addons/__init__.py
odoo/addons/mass_mailing/README.md
odoo/addons/mass_mailing/__init__.py
odoo/addons/mass_mailing/__manifest__.py
odoo/addons/mass_mailing/controllers/__init__.py
odoo/addons/mass_mailing/controllers/main.py
odoo/addons/mass_mailing/controllers/web_editor.py
odoo/addons/mass_mailing/data/mass_mailing_data.xml
odoo/addons/mass_mailing/data/mass_mailing_demo.xml
odoo/addons/mass_mailing/doc/changelog.rst
odoo/addons/mass_mailing/doc/index.rst
odoo/addons/mass_mailing/i18n/af.po
odoo/addons/mass_mailing/i18n/am.po
odoo/addons/mass_mailing/i18n/ar.po
odoo/addons/mass_mailing/i18n/bg.po
odoo/addons/mass_mailing/i18n/bs.po
odoo/addons/mass_mailing/i18n/ca.po
odoo/addons/mass_mailing/i18n/cs.po
odoo/addons/mass_mailing/i18n/da.po
odoo/addons/mass_mailing/i18n/de.po
odoo/addons/mass_mailing/i18n/el.po
odoo/addons/mass_mailing/i18n/en_GB.po
odoo/addons/mass_mailing/i18n/es.po
odoo/addons/mass_mailing/i18n/es_BO.po
odoo/addons/mass_mailing/i18n/es_CL.po
odoo/addons/mass_mailing/i18n/es_CO.po
odoo/addons/mass_mailing/i18n/es_CR.po
odoo/addons/mass_mailing/i18n/es_DO.po
odoo/addons/mass_mailing/i18n/es_EC.po
odoo/addons/mass_mailing/i18n/es_PE.po
odoo/addons/mass_mailing/i18n/es_PY.po
odoo/addons/mass_mailing/i18n/es_VE.po
odoo/addons/mass_mailing/i18n/et.po
odoo/addons/mass_mailing/i18n/eu.po
odoo/addons/mass_mailing/i18n/fa.po
odoo/addons/mass_mailing/i18n/fi.po
odoo/addons/mass_mailing/i18n/fo.po
odoo/addons/mass_mailing/i18n/fr.po
odoo/addons/mass_mailing/i18n/fr_BE.po
odoo/addons/mass_mailing/i18n/fr_CA.po
odoo/addons/mass_mailing/i18n/gl.po
odoo/addons/mass_mailing/i18n/gu.po
odoo/addons/mass_mailing/i18n/he.po
odoo/addons/mass_mailing/i18n/hr.po
odoo/addons/mass_mailing/i18n/hu.po
odoo/addons/mass_mailing/i18n/id.po
odoo/addons/mass_mailing/i18n/is.po
odoo/addons/mass_mailing/i18n/it.po
odoo/addons/mass_mailing/i18n/ja.po
odoo/addons/mass_mailing/i18n/ka.po
odoo/addons/mass_mailing/i18n/kab.po
odoo/addons/mass_mailing/i18n/ko.po
odooku_odoo_mass_mailing-11.0.7.dist-info/LICENSE
odooku_odoo_mass_mailing-11.0.7.dist-info/METADATA
odooku_odoo_mass_mailing-11.0.7.dist-info/WHEEL
odooku_odoo_mass_mailing-11.0.7.dist-info/top_level.txt
odooku_odoo_mass_mailing-11.0.7.dist-info/RECORD
